aguasgaia/__init__.py
aguasgaia/aguasgaia.py
aguasgaia/const.py
aguasgaia/models/__init__.py
aguasgaia/models/consumption.py
aguasgaia/models/invoice.py
aguasgaia/models/subscription.py
src/aguasgaia/__init__.py
src/aguasgaia/models/__init__.py
src/aguasgaia/models/consumption.py
src/aguasgaia/models/invoice.py
tests/aguasgaia_test.py
aguasgaia-0.0.21.dist-info/LICENSE
aguasgaia-0.0.21.dist-info/METADATA
aguasgaia-0.0.21.dist-info/WHEEL
aguasgaia-0.0.21.dist-info/top_level.txt
aguasgaia-0.0.21.dist-info/RECORD
