Metadata-Version: 2.1
Name: aguasgaia
Version: 0.0.21
Summary: Python library to retrieve information from "Aguas de Gaia" portal
Author-email: Jose Rolo <ze.p.rolo@gmail.com>
License: Apache-2.0
Keywords: api,aguasgaia
Classifier: Programming Language :: Python :: 3
Requires-Python: >=3
License-File: LICENSE
Requires-Dist: aiohttp
Requires-Dist: python-dateutil
